odoo/addons/stock_budget_plan_detail/README.rst
odoo/addons/stock_budget_plan_detail/__init__.py
odoo/addons/stock_budget_plan_detail/__manifest__.py
odoo/addons/stock_budget_plan_detail/hooks.py
odoo/addons/stock_budget_plan_detail/models/__init__.py
odoo/addons/stock_budget_plan_detail/models/account_analytic_dimension.py
odoo/addons/stock_budget_plan_detail/models/stock_move.py
odoo/addons/stock_budget_plan_detail/models/stock_move_line.py
odoo/addons/stock_budget_plan_detail/models/stock_rule.py
odoo/addons/stock_budget_plan_detail/models/stock_scrap.py
odoo/addons/stock_budget_plan_detail/readme/CONTRIBUTORS.md
odoo/addons/stock_budget_plan_detail/readme/DESCRIPTION.md
odoo/addons/stock_budget_plan_detail/static/description/icon.png
odoo/addons/stock_budget_plan_detail/static/description/index.html
odoo/addons/stock_budget_plan_detail/tests/__init__.py
odoo/addons/stock_budget_plan_detail/tests/test_stock_picking_budget_plan_detail.py
odoo/addons/stock_budget_plan_detail/tests/test_stock_scrap_budget_plan_detail.py
odoo/addons/stock_budget_plan_detail/views/stock_move_line.xml
odoo/addons/stock_budget_plan_detail/views/stock_move_views.xml
odoo/addons/stock_budget_plan_detail/views/stock_picking_views.xml
odoo/addons/stock_budget_plan_detail/views/stock_scrap.xml
odoo_addon_stock_budget_plan_detail-18.0.1.0.1.dist-info/METADATA
odoo_addon_stock_budget_plan_detail-18.0.1.0.1.dist-info/WHEEL
odoo_addon_stock_budget_plan_detail-18.0.1.0.1.dist-info/top_level.txt
odoo_addon_stock_budget_plan_detail-18.0.1.0.1.dist-info/RECORD
